zfit_physics/__init__.py
zfit_physics/_version.py
zfit_physics/pdf.py
zfit_physics/compwa/__init__.py
zfit_physics/compwa/data.py
zfit_physics/compwa/loss.py
zfit_physics/compwa/pdf.py
zfit_physics/compwa/variables.py
zfit_physics/models/__init__.py
zfit_physics/models/pdf_argus.py
zfit_physics/models/pdf_cmsshape.py
zfit_physics/models/pdf_conv.py
zfit_physics/models/pdf_cruijff.py
zfit_physics/models/pdf_erfexp.py
zfit_physics/models/pdf_example.py
zfit_physics/models/pdf_kde.py
zfit_physics/models/pdf_novosibirsk.py
zfit_physics/models/pdf_relbw.py
zfit_physics/models/pdf_tsallis.py
zfit_physics/pyhf/__init__.py
zfit_physics/pyhf/loss.py
zfit_physics/roofit/__init__.py
zfit_physics/roofit/loss.py
zfit_physics/roofit/variables.py
zfit_physics/tfpwa/__init__.py
zfit_physics/tfpwa/loss.py
zfit_physics/tfpwa/variables.py
zfit_physics/unstable/__init__.py
zfit_physics/unstable/pdf.py
zfit_physics-0.8.1.dist-info/METADATA
zfit_physics-0.8.1.dist-info/WHEEL
zfit_physics-0.8.1.dist-info/licenses/LICENSE
zfit_physics-0.8.1.dist-info/RECORD
