Metadata-Version: 2.4
Name: zfit_physics
Version: 0.8.1
Summary: Physics extension to zfit
Project-URL: Documentation, https://zfit-physics.readthedocs.io/en/latest/
Project-URL: Repository, https://github.com/zfit/zfit-physics
Project-URL: Bug Tracker, https://github.com/zfit/zfit-physics/issues
Project-URL: Discussions, https://github.com/zfit/zfit-physics/discussions
Project-URL: Changelog, https://github.com/zfit/zfit-physics/blob/main/CHANGELOG.rst
License: BSD 3-Clause License
License-File: LICENSE
Keywords: TensorFlow, model, fitting, scalable, HEP, physics
Classifier: Development Status :: 4 - Beta
Classifier: Intended Audience :: Science/Research
Classifier: License :: OSI Approved :: BSD License
Classifier: Natural Language :: English
Classifier: Operating System :: MacOS
Classifier: Operating System :: Unix
Classifier: Programming Language :: Python :: 3
Classifier: Programming Language :: Python :: 3 :: Only
Classifier: Programming Language :: Python :: 3.9
Classifier: Programming Language :: Python :: 3.10
Classifier: Programming Language :: Python :: 3.11
Classifier: Programming Language :: Python :: 3.12
Classifier: Programming Language :: Python :: Implementation :: CPython
Classifier: Topic :: Scientific/Engineering :: Physics
Requires-Python: >=3.9
Requires-Dist: zfit>=0.20
Provides-Extra: all
Requires-Dist: ampform; extra == 'all'
Requires-Dist: pyhf; extra == 'all'
Requires-Dist: qrules; extra == 'all'
Requires-Dist: tensorwaves[phsp]; extra == 'all'
Requires-Dist: tfpwa>=0.2.2; extra == 'all'
Provides-Extra: compwa
Requires-Dist: ampform; extra == 'compwa'
Requires-Dist: qrules; extra == 'compwa'
Requires-Dist: tensorwaves[phsp]; extra == 'compwa'
Provides-Extra: dev
Requires-Dist: ampform; extra == 'dev'
Requires-Dist: bumpversion>=0.5.3; extra == 'dev'
Requires-Dist: contextlib-chdir; extra == 'dev'
Requires-Dist: coverage>=4.5.1; extra == 'dev'
Requires-Dist: flake8>=3.5.0; extra == 'dev'
Requires-Dist: jupyter-sphinx; extra == 'dev'
Requires-Dist: myst-nb; extra == 'dev'
Requires-Dist: numba-stats; extra == 'dev'
Requires-Dist: pip>=9.0.1; extra == 'dev'
Requires-Dist: pre-commit; extra == 'dev'
Requires-Dist: pydata-sphinx-theme>=0.9; extra == 'dev'
Requires-Dist: pyhf; extra == 'dev'
Requires-Dist: pytest; extra == 'dev'
Requires-Dist: pytest-cov; extra == 'dev'
Requires-Dist: pytest-rerunfailures; extra == 'dev'
Requires-Dist: pytest-xdist; extra == 'dev'
Requires-Dist: pyyaml; extra == 'dev'
Requires-Dist: qrules; extra == 'dev'
Requires-Dist: seed-intersphinx-mapping; extra == 'dev'
Requires-Dist: setupext-janitor; extra == 'dev'
Requires-Dist: sphinx-autodoc-typehints; extra == 'dev'
Requires-Dist: sphinx-copybutton; extra == 'dev'
Requires-Dist: sphinx-panels; extra == 'dev'
Requires-Dist: sphinx-togglebutton; extra == 'dev'
Requires-Dist: sphinx>=3.5.4; extra == 'dev'
Requires-Dist: sphinxcontrib-applehelp<1.0.8; extra == 'dev'
Requires-Dist: sphinxcontrib-images; extra == 'dev'
Requires-Dist: sphinxcontrib-youtube<1.2.0,>=1.0.0; extra == 'dev'
Requires-Dist: tensorwaves[phsp]; extra == 'dev'
Requires-Dist: tfpwa>=0.2.2; extra == 'dev'
Requires-Dist: tox>=2.9.1; extra == 'dev'
Requires-Dist: twine>=1.10.0; extra == 'dev'
Requires-Dist: watchdog>=0.8.3; extra == 'dev'
Requires-Dist: wheel>=0.29.0; extra == 'dev'
Provides-Extra: pyhf
Requires-Dist: pyhf; extra == 'pyhf'
Provides-Extra: test
Requires-Dist: ampform; extra == 'test'
Requires-Dist: contextlib-chdir; extra == 'test'
Requires-Dist: pyhf; extra == 'test'
Requires-Dist: pytest; extra == 'test'
Requires-Dist: pytest-cov; extra == 'test'
Requires-Dist: pytest-rerunfailures; extra == 'test'
Requires-Dist: pytest-xdist; extra == 'test'
Requires-Dist: qrules; extra == 'test'
Requires-Dist: tensorwaves[phsp]; extra == 'test'
Requires-Dist: tfpwa>=0.2.2; extra == 'test'
Provides-Extra: tfpwa
Requires-Dist: tfpwa>=0.2.2; extra == 'tfpwa'
